tech_aouyi_mcp_last/__init__.py
tech_aouyi_mcp_last-0.1.3.dist-info/WHEEL
tech_aouyi_mcp_last-0.1.3.dist-info/entry_points.txt
tech_aouyi_mcp_last-0.1.3.dist-info/METADATA
tech_aouyi_mcp_last-0.1.3.dist-info/RECORD
